autocolorize/__init__.py
autocolorize/__main__.py
autocolorize/checker.py
autocolorize/color.py
autocolorize/config.py
autocolorize/datasets.py
autocolorize/download.py
autocolorize/extraction.py
autocolorize/image.py
autocolorize/res/__init__.py
autocolorize/res/autocolorize.prototxt.template
autocolorize-0.2.1.data/scripts/autocolorize
autocolorize-0.2.1.dist-info/DESCRIPTION.rst
autocolorize-0.2.1.dist-info/METADATA
autocolorize-0.2.1.dist-info/RECORD
autocolorize-0.2.1.dist-info/WHEEL
autocolorize-0.2.1.dist-info/metadata.json
autocolorize-0.2.1.dist-info/top_level.txt
