Metadata-Version: 2.0
Name: autocolorize
Version: 0.2.1
Summary: Automatic colorizaton of grayscale images using Deep Learning.
Home-page: https://github.com/gustavla/autocolorize
Author: Gustav Larsson
Author-email: gustav.m.larsson@gmail.com
License: BSD
Platform: UNKNOWN
Classifier: Development Status :: 4 - Beta
Classifier: Intended Audience :: Science/Research
Classifier: License :: OSI Approved :: BSD License
Classifier: Programming Language :: Python
Classifier: Programming Language :: Python :: 2
Classifier: Programming Language :: Python :: 2.7
Classifier: Programming Language :: Python :: 3
Classifier: Programming Language :: Python :: 3.4
Classifier: Topic :: Scientific/Engineering
Requires-Dist: numpy
Requires-Dist: requests
Requires-Dist: scikit-image
Requires-Dist: scipy
